setup.py
digAddressExtractor/__init__.py
digAddressExtractor/address_extractor.py
digAddressExtractor.egg-info/PKG-INFO
digAddressExtractor.egg-info/SOURCES.txt
digAddressExtractor.egg-info/dependency_links.txt
digAddressExtractor.egg-info/requires.txt
digAddressExtractor.egg-info/top_level.txt
test/__init__.py
test/test_address_extractor.py