Metadata-Version: 1.1
Name: digAddressExtractor
Version: 0.3.0
Summary: digAddressExtractor
Home-page: https://github.com/usc-isi-i2/dig-address-extractor
Author: Lingzhe Teng
Author-email: zwein27@gmail.com
License: UNKNOWN
Download-URL: https://github.com/usc-isi-i2/dig-address-extractor
Keywords: address,extractor
Platform: UNKNOWN
